zombie-web/__init__.py
zombie-web/default_settings.py
zombie-web/downloader.py
zombie-web/parse.py
zombie-web/pipeline.py
zombie-web/reachable.py
zombie-web/schedule.py
zombie-web/utils.py
zombie-web/zombie.py
zombie_core/__init__.py
zombie_core/default_settings.py
zombie_core/downloader.py
zombie_core/parse.py
zombie_core/pipeline.py
zombie_core/reachable.py
zombie_core/schedule.py
zombie_core/utils.py
zombie_core/zombie.py
zombie_web/__init__.py
zombie_web/default_settings.py
zombie_web/downloader.py
zombie_web/parse.py
zombie_web/pipeline.py
zombie_web/reachable.py
zombie_web/schedule.py
zombie_web/utils.py
zombie_web/zombie.py
zombie_core-0.0.2.dist-info/METADATA
zombie_core-0.0.2.dist-info/WHEEL
zombie_core-0.0.2.dist-info/top_level.txt
zombie_core-0.0.2.dist-info/RECORD
