Metadata-Version: 2.1
Name: zombie-core
Version: 0.0.2
Summary: zombie tools for web
Home-page: https://github.com/billsteve
Author: bill steve
Author-email: billsteve@126.com
Maintainer: bill steve
Maintainer-email: billsteve@126.com
License: MIT License
Platform: all
Classifier: Programming Language :: Python :: 3.6
Classifier: Topic :: Software Development :: Libraries
Requires-Dist: scrapy
Requires-Dist: scrapyd
Requires-Dist: scrapyd-client
Requires-Dist: scrapy-redis
Requires-Dist: pyquery
Requires-Dist: redis
Requires-Dist: requests
Requires-Dist: pymysql
Requires-Dist: sqlalchemy
Requires-Dist: logzero
Requires-Dist: happybase
Requires-Dist: tld
